comment.py
accepts/__init__.py
afk_tracker/__init__.py
afk_tracker/apps.py
afk_tracker/classes.py
afk_tracker/models.py
afk_tracker/setup.py
afk_tracker/migrations/0001_initial.py
afk_tracker/migrations/__init__.py
applescript/__init__.py
applescript/tell.py
badge/__init__.py
cached/__init__.py
ccmenu/__init__.py
ccmenu/preferences.py
ccmenu/restart.py
ccmenu/projects/__init__.py
ccmenu/projects/add.py
ccmenu/projects/clear.py
ccmenu/projects/names.py
ccmenu/projects/rm.py
ccmenu/projects/urls.py
ccmenu/travis/__init__.py
ccmenu/travis/add.py
ccmenu/travis/clear.py
ccmenu/travis/set.py
chmod/__init__.py
chmod/check.py
chmod/make.py
classifiers/__init__.py
classifiers_generator/__init__.py
classifiers_generator/__main__.py
cls/__init__.py
columnate/__init__.py
connection/__init__.py
control_characters/__init__.py
stdin/__init__.py
control_characters-2019.3.22.dist-info/METADATA
control_characters-2019.3.22.dist-info/WHEEL
control_characters-2019.3.22.dist-info/top_level.txt
control_characters-2019.3.22.dist-info/RECORD
